[{"album":"Falling","status":"ADD","artist":{"image_url":"http://songza.com/api/1/artist/511acd3fe9e23d724dee660c/image","id":"511acd3fe9e23d724dee660c","name":"HAIM"},"external_media":{"youtube":{"id":"AIjVpRAXK18"}},"title":"Falling (Psychemagik Remix)","cover_url":"http://images.mndigital.com/albums/082/735/915/g.jpeg","genre":"Alternative/Indie","pa":false,"quality_issues":[],"formats":[{"available":true,"format":"aac"},{"available":true,"format":"mp3"}],"duration":354,"new":false,"id":25893909,"added_by":null},{"album":"In The Grace Of Your Love - Deluxe Edition","status":"ADD","artist":{"image_url":"http://songza.com/api/1/artist/511ac4d1e9e23d724de916b4/image","id":"511ac4d1e9e23d724de916b4","name":"The Rapture"},"external_media":{"youtube":{"id":"7qfxCvwyxms"}},"title":"How Deep Is Your Love? (A-Trak Remix)","cover_url":"http://images.mndigital.com/albums/067/134/745/g.jpeg","genre":"Electronica/Dance","pa":false,"quality_issues":[],"formats":[{"available":true,"format":"aac"},{"available":true,"format":"mp3"}],"duration":388,"new":false,"id":19455872,"added_by":null},{"album":"TNGHT","status":"ADD","artist":{"image_url":"http://songza.com/api/1/artist/511acc5de9e23d724dedd37c/image","id":"511acc5de9e23d724dedd37c","name":"TNGHT"},"external_media":{"youtube":{"id":"6HzyUHxmkg0"}},"title":"Higher Ground","cover_url":"http://images.mndigital.com/albums/069/854/243/g.jpeg","genre":"Electronica/Dance","pa":false,"quality_issues":[],"formats":[{"available":true,"format":"aac"},{"available":true,"format":"mp3"}],"duration":199,"new":false,"id":20459632,"added_by":null},{"album":"On A Mission","status":"ADD","artist":{"image_url":"http://songza.com/api/1/artist/511ace4de9e23d724def09de/image","id":"511ace4de9e23d724def09de","name":"Katy B"},"external_media":{"youtube":{"id":"HkmET8y-RiM"}},"title":"Witches Brew","cover_url":"http://images.mndigital.com/albums/052/005/283/g.jpeg","genre":"Pop","pa":false,"quality_issues":[],"formats":[{"available":true,"format":"aac"},{"available":true,"format":"mp3"}],"duration":201,"new":false,"id":15997929,"added_by":null},{"album":"Remix","status":"ADD","artist":{"image_url":"http://songza.com/api/1/artist/511ac481e9e23d724de8e2d0/image","id":"511ac481e9e23d724de8e2d0","name":"Le Tigre"},"external_media":{"youtube":{"id":"EU1CDSP7FRk"}},"title":"Deceptacon (Dfa Remix)","cover_url":"http://images.mndigital.com/albums/031/034/089/g.jpeg","genre":"Rock","pa":false,"quality_issues":[{"type":"no-match-in-google-play-music"}],"formats":[{"available":true,"format":"aac"},{"available":true,"format":"mp3"}],"duration":384,"new":false,"id":5419246,"added_by":null},{"album":"Around The World","status":"ADD","artist":{"image_url":"http://songza.com/api/1/artist/511acd96e9e23d724dee9b43/image","id":"511acd96e9e23d724dee9b43","name":"Daft Punk"},"external_media":{"youtube":{"id":"s9MszVE7aR4"}},"title":"Around The World","cover_url":"http://images.mndigital.com/albums/004/547/855/g.jpeg","genre":"Electronica/Dance","pa":false,"quality_issues":[],"formats":[{"available":true,"format":"aac"},{"available":true,"format":"mp3"}],"duration":430,"new":false,"id":11960660,"added_by":null},{"album":"Genesis","status":"ADD","artist":{"image_url":"http://songza.com/api/1/artist/511acd54e9e23d724dee72c2/image","id":"511acd54e9e23d724dee72c2","name":"Grimes"},"external_media":{"youtube":{"id":"1FH-q0I1fJY"}},"title":"Genesis","cover_url":"http://images.mndigital.com/albums/064/478/333/g.jpeg","genre":"Electronica/Dance","pa":false,"quality_issues":[],"formats":[{"available":true,"format":"aac"},{"available":true,"format":"mp3"}],"duration":255,"new":false,"id":18617187,"added_by":null},{"album":"Discovery","status":"ADD","artist":{"image_url":"http://songza.com/api/1/artist/511acd96e9e23d724dee9b43/image","id":"511acd96e9e23d724dee9b43","name":"Daft Punk"},"external_media":{"youtube":{"id":"FGBhQbmPwH8"}},"title":"One More Time","cover_url":"http://images.mndigital.com/albums/000/091/851/g.jpeg","genre":"Electronica/Dance","pa":false,"quality_issues":[],"formats":[{"available":true,"format":"aac"},{"available":true,"format":"mp3"}],"duration":321,"new":false,"id":17616754,"added_by":null},{"album":"Myths Of The Near Future","status":"ADD","artist":{"image_url":"http://songza.com/api/1/artist/511acc68e9e23d724dedda62/image","id":"511acc68e9e23d724dedda62","name":"Klaxons"},"external_media":{"youtube":{"id":"XX3w_PlGReU"}},"title":"Atlantis To Interzone","cover_url":"http://images.mndigital.com/albums/009/658/989/g.jpeg","genre":"Electronica/Dance","pa":false,"quality_issues":[],"formats":[{"available":true,"format":"aac"},{"available":true,"format":"mp3"}],"duration":195,"new":false,"id":12760672,"added_by":null},{"album":"Midnight City","status":"ADD","artist":{"image_url":"http://songza.com/api/1/artist/511ace32e9e23d724deefd70/image","id":"511ace32e9e23d724deefd70","name":"M83"},"title":"Midnight City","cover_url":"http://images.mndigital.com/albums/099/348/279/g.jpeg","genre":"Pop","pa":false,"quality_issues":[],"formats":[{"available":true,"format":"aac"},{"available":true,"format":"mp3"}],"duration":242,"new":false,"id":30125175,"added_by":null},{"album":"Ice Cream","status":"ADD","artist":{"image_url":"http://songza.com/api/1/artist/511acc46e9e23d724dedc467/image","id":"511acc46e9e23d724dedc467","name":"Battles"},"external_media":{"youtube":{"id":"-CXtJA34QGQ"}},"title":"Ice Cream (Featuring Matias Aguayo)","cover_url":"http://images.mndigital.com/albums/053/846/391/g.jpeg","genre":"Alternative/Indie","pa":false,"quality_issues":[{"type":"isrc-is-missing"}],"formats":[{"available":true,"format":"aac"},{"available":true,"format":"mp3"}],"duration":277,"new":false,"id":11699537,"added_by":null},{"album":"212 (Feat. Lazy Jay) - Single","status":"ADD","artist":{"image_url":"http://songza.com/api/1/artist/511acc51e9e23d724dedcc21/image","id":"511acc51e9e23d724dedcc21","name":"Azealia Banks"},"external_media":{"youtube":{"id":"i3Jv9fNPjgk"}},"title":"212 (Feat. Lazy Jay)","cover_url":"http://images.mndigital.com/albums/063/048/911/g.jpeg","genre":"Rap/Hip Hop","pa":true,"quality_issues":[{"type":"no-match-in-google-play-music"}],"formats":[{"available":true,"format":"aac"},{"available":true,"format":"mp3"}],"duration":205,"new":false,"id":18089823,"added_by":null},{"album":"Heartthrob","status":"ADD","artist":{"image_url":"http://songza.com/api/1/artist/511ace49e9e23d724def0777/image","id":"511ace49e9e23d724def0777","name":"Tegan and Sara"},"external_media":{"youtube":{"id":"9e9NSMY8QiQ"}},"title":"Closer","cover_url":"http://images.mndigital.com/albums/079/567/755/g.jpeg","genre":"Alternative/Indie","pa":false,"quality_issues":[],"formats":[{"available":true,"format":"aac"},{"available":true,"format":"mp3"}],"duration":210,"new":false,"id":24561071,"added_by":null},{"album":"Feed Me Diamonds","status":"ADD","artist":{"image_url":"http://songza.com/api/1/artist/511ac993e9e23d724dec1a22/image","id":"511ac993e9e23d724dec1a22","name":"MNDR"},"external_media":{"youtube":{"id":"eSm-HANfCHE"}},"title":"#1 In Heaven","cover_url":"http://images.mndigital.com/albums/071/636/045/g.jpeg","genre":"Electronica/Dance","pa":false,"quality_issues":[{"type":"song-is-forwarded"}],"formats":[{"available":true,"format":"aac"},{"available":true,"format":"mp3"}],"duration":231,"new":false,"id":21387764,"added_by":null},{"album":"Discovery","status":"ADD","artist":{"image_url":"http://songza.com/api/1/artist/511acd96e9e23d724dee9b43/image","id":"511acd96e9e23d724dee9b43","name":"Daft Punk"},"external_media":{"youtube":{"id":"K2cYWfq--Nw"}},"title":"Harder, Better, Faster, Stronger","cover_url":"http://images.mndigital.com/albums/000/091/851/g.jpeg","genre":"Electronica/Dance","pa":false,"quality_issues":[],"formats":[{"available":true,"format":"aac"},{"available":true,"format":"mp3"}],"duration":225,"new":false,"id":17627253,"added_by":null},{"album":"Settle","status":"ADD","artist":{"image_url":"http://songza.com/api/1/artist/511ace22e9e23d724deef301/image","id":"511ace22e9e23d724deef301","name":"Disclosure"},"external_media":{"youtube":{"id":"bkk2H3Ztrfk"}},"title":"White Noise","cover_url":"http://images.mndigital.com/albums/084/987/153/g.jpeg","genre":"Electronica/Dance","pa":false,"quality_issues":[],"formats":[{"available":true,"format":"aac"},{"available":true,"format":"mp3"}],"duration":278,"new":false,"id":26641011,"added_by":null},{"album":"Express Yourself","status":"ADD","artist":{"image_url":"http://songza.com/api/1/artist/511ace33e9e23d724deefdea/image","id":"511ace33e9e23d724deefdea","name":"Diplo"},"external_media":{"youtube":{"id":"BKaL7WL-onI"}},"title":"Express Yourself (Feat. Nicky Da B)","cover_url":"http://images.mndigital.com/albums/065/635/987/g.jpeg","genre":"Electronica/Dance","pa":false,"quality_issues":[],"formats":[{"available":true,"format":"aac"},{"available":true,"format":"mp3"}],"duration":277,"new":false,"id":19082791,"added_by":null},{"album":"Made In The Dark","status":"ADD","artist":{"image_url":"http://songza.com/api/1/artist/511acd9ae9e23d724dee9d5c/image","id":"511acd9ae9e23d724dee9d5c","name":"Hot Chip"},"external_media":{"youtube":{"id":"yhASu2OjEcQ"}},"title":"Ready For The Floor","cover_url":"http://images.mndigital.com/albums/012/695/617/g.jpeg","genre":"Alternative/Indie","pa":false,"quality_issues":[],"formats":[{"available":true,"format":"aac"},{"available":true,"format":"mp3"}],"duration":235,"new":false,"id":2540754,"added_by":null},{"album":"I Love It","status":"ADD","artist":{"image_url":"http://songza.com/api/1/artist/511acd4ae9e23d724dee6c99/image","id":"511acd4ae9e23d724dee6c99","name":"Icona Pop"},"external_media":{"youtube":{"id":"UxxajLWwzqY"}},"title":"I Love It","cover_url":"http://images.mndigital.com/albums/071/962/169/g.jpeg","genre":"Electronica/Dance","pa":true,"quality_issues":[],"formats":[{"available":true,"format":"aac"},{"available":true,"format":"mp3"}],"duration":156,"new":false,"id":21534295,"added_by":null},{"album":"Rapprocher","status":"ADD","artist":{"image_url":"http://songza.com/api/1/artist/511acca4e9e23d724dee01e6/image","id":"511acca4e9e23d724dee01e6","name":"Class Actress"},"external_media":{"youtube":{"id":"5XdTr23ABQk"}},"title":"Weekend","cover_url":"http://images.mndigital.com/albums/059/355/103/g.jpeg","genre":"Pop","pa":false,"quality_issues":[],"formats":[{"available":true,"format":"aac"},{"available":true,"format":"mp3"}],"duration":242,"new":false,"id":14528096,"added_by":null},{"album":"Red Lips","status":"ADD","artist":{"image_url":"http://songza.com/api/1/artist/511acdf2e9e23d724deed52d/image","id":"511acdf2e9e23d724deed52d","name":"Sky Ferreira"},"external_media":{"youtube":{"id":"HoCqCrH8aBM"}},"title":"Red Lips","cover_url":"http://images.mndigital.com/albums/070/139/773/g.jpeg","genre":"Pop","pa":false,"quality_issues":[{"type":"song-is-forwarded"}],"formats":[{"available":true,"format":"aac"},{"available":true,"format":"mp3"}],"duration":142,"new":false,"id":20585016,"added_by":null},{"album":"You Put A Smell On Me","status":"ADD","artist":{"image_url":"http://songza.com/api/1/artist/511ace33e9e23d724deefdce/image","id":"511ace33e9e23d724deefdce","name":"Matthew Dear"},"external_media":{"youtube":{"id":"ZnU_16mXMNw"}},"title":"You Put A Smell On Me","cover_url":"http://images.mndigital.com/albums/047/646/873/g.jpeg","genre":"Electronica/Dance","pa":false,"quality_issues":[],"formats":[{"available":true,"format":"aac"},{"available":true,"format":"mp3"}],"duration":304,"new":false,"id":16766816,"added_by":null},{"album":"Die Slow","status":"ADD","artist":{"image_url":"http://songza.com/api/1/artist/511ac7d1e9e23d724deafd33/image","id":"511ac7d1e9e23d724deafd33","name":"Health"},"external_media":{"youtube":{"id":"EWZxThGh5wQ"}},"title":"Die Slow","cover_url":"http://images.mndigital.com/albums/086/858/353/g.jpeg","genre":"Alternative/Indie","pa":false,"quality_issues":[],"formats":[{"available":true,"format":"aac"},{"available":true,"format":"mp3"}],"duration":194,"new":false,"id":27034102,"added_by":null},{"album":"La Roux","status":"ADD","artist":{"image_url":"http://songza.com/api/1/artist/511acc43e9e23d724dedc2ae/image","id":"511acc43e9e23d724dedc2ae","name":"La Roux"},"external_media":{"youtube":{"id":"Kk8eJh4i8Lo"}},"title":"Bulletproof","cover_url":"http://images.mndigital.com/albums/033/242/983/g.jpeg","genre":"Pop","pa":false,"quality_issues":[],"formats":[{"available":true,"format":"aac"},{"available":true,"format":"mp3"}],"duration":206,"new":false,"id":6041825,"added_by":null},{"album":"Cross","status":"ADD","artist":{"image_url":"http://songza.com/api/1/artist/511acbf4e9e23d724ded9054/image","id":"511acbf4e9e23d724ded9054","name":"Justice"},"external_media":{"youtube":{"id":"VKzWLUQizz8"}},"title":"Genesis","cover_url":"http://images.mndigital.com/albums/011/106/333/g.jpeg","genre":"Electronica/Dance","pa":false,"quality_issues":[],"formats":[{"available":true,"format":"aac"},{"available":true,"format":"mp3"}],"duration":235,"new":false,"id":2217796,"added_by":null},{"album":"Helicopter","status":"ADD","artist":{"image_url":"http://songza.com/api/1/artist/511acc68e9e23d724deddaa6/image","id":"511acc68e9e23d724deddaa6","name":"Bloc Party"},"title":"Helicopter (Diplo Remix)","cover_url":"http://images.mndigital.com/albums/106/398/713/g.jpeg","genre":"Electronica/Dance","pa":false,"quality_issues":[],"formats":[{"available":true,"format":"aac"},{"available":true,"format":"mp3"}],"duration":305,"new":false,"id":31550260,"added_by":null},{"album":"Kala","status":"ADD","artist":{"image_url":"http://songza.com/api/1/artist/511ac448e9e23d724de8be78/image","id":"511ac448e9e23d724de8be78","name":"M.I.A."},"external_media":{"youtube":{"id":"wcN1i6Qcjxg"}},"title":"Boyz","cover_url":"http://images.mndigital.com/albums/011/000/203/g.jpeg","genre":"Electronica/Dance","pa":false,"quality_issues":[],"formats":[{"available":true,"format":"aac"},{"available":true,"format":"mp3"}],"duration":207,"new":false,"id":18334873,"added_by":null},{"album":"True Romance","status":"ADD","artist":{"image_url":"http://songza.com/api/1/artist/511acdafe9e23d724deeab46/image","id":"511acdafe9e23d724deeab46","name":"Charli XCX"},"external_media":{"youtube":{"id":"S7cOt-xFU8Y"}},"title":"Take My Hand","cover_url":"http://images.mndigital.com/albums/082/632/583/g.jpeg","genre":"Pop","pa":true,"quality_issues":[],"formats":[{"available":true,"format":"aac"},{"available":true,"format":"mp3"}],"duration":267,"new":false,"id":25838948,"added_by":null},{"album":"In Ghost Colours","status":"ADD","artist":{"image_url":"http://songza.com/api/1/artist/511acdf3e9e23d724deed636/image","id":"511acdf3e9e23d724deed636","name":"Cut Copy"},"external_media":{"youtube":{"id":"Bdn0MYDATtE"}},"title":"Hearts On Fire","cover_url":"http://images.mndigital.com/albums/013/487/789/g.jpeg","genre":"Electronica/Dance","pa":false,"quality_issues":[],"formats":[{"available":true,"format":"aac"},{"available":true,"format":"mp3"}],"duration":293,"new":false,"id":2698306,"added_by":null},{"album":"LCD Soundsystem","status":"ADD","artist":{"image_url":"http://songza.com/api/1/artist/511acce3e9e23d724dee2ac8/image","id":"511acce3e9e23d724dee2ac8","name":"LCD Soundsystem"},"external_media":{"youtube":{"id":"A7NapIkIiIk"}},"title":"Tribulations","cover_url":"http://images.mndigital.com/albums/003/526/507/g.jpeg","genre":"Alternative/Indie","pa":false,"quality_issues":[],"formats":[{"available":true,"format":"aac"},{"available":true,"format":"mp3"}],"duration":299,"new":false,"id":674192,"added_by":null},{"album":"Something","status":"ADD","artist":{"image_url":"http://songza.com/api/1/artist/511acb50e9e23d724ded2749/image","id":"511acb50e9e23d724ded2749","name":"Chairlift"},"external_media":{"youtube":{"id":"j_aTOyFRwJ0"}},"title":"I Belong In Your Arms","cover_url":"http://images.mndigital.com/albums/063/420/341/g.jpeg","genre":"Alternative/Indie","pa":false,"quality_issues":[],"formats":[{"available":true,"format":"aac"},{"available":true,"format":"mp3"}],"duration":207,"new":false,"id":18176341,"added_by":null},{"album":"Witching Hour","status":"ADD","artist":{"image_url":"http://songza.com/api/1/artist/511acb75e9e23d724ded3f01/image","id":"511acb75e9e23d724ded3f01","name":"Ladytron"},"external_media":{"youtube":{"id":"JTTwlAT_AwU"}},"title":"Destroy Everything You Touch","cover_url":"http://images.mndigital.com/albums/005/273/773/g.jpeg","genre":"Electronica/Dance","pa":false,"quality_issues":[],"formats":[{"available":true,"format":"aac"},{"available":true,"format":"mp3"}],"duration":276,"new":false,"id":1001907,"added_by":null},{"album":"Cansei De Ser Sexy","status":"ADD","artist":{"image_url":"http://songza.com/api/1/artist/511acb0ae9e23d724decfb07/image","id":"511acb0ae9e23d724decfb07","name":"CSS"},"external_media":{"youtube":{"id":"7agPOt1XZz8"}},"title":"Let's Make Love And Listen Death From Above","cover_url":"http://images.mndigital.com/albums/009/561/619/g.jpeg","genre":"Pop","pa":false,"quality_issues":[],"formats":[{"available":true,"format":"aac"},{"available":true,"format":"mp3"}],"duration":211,"new":false,"id":25504938,"added_by":null},{"album":"Master Of My Make-Believe","status":"ADD","artist":{"image_url":"http://songza.com/api/1/artist/511acd94e9e23d724dee99f2/image","id":"511acd94e9e23d724dee99f2","name":"Santigold"},"external_media":{"youtube":{"id":"c0U4AUTbDC8"}},"title":"Go! (Feat. Karen O)","cover_url":"http://images.mndigital.com/albums/066/659/407/g.jpeg","genre":"Alternative/Indie","pa":false,"quality_issues":[],"formats":[{"available":true,"format":"aac"},{"available":true,"format":"mp3"}],"duration":204,"new":false,"id":19351460,"added_by":null},{"album":"Mixed Emotions","status":"ADD","artist":{"image_url":"http://songza.com/api/1/artist/511ac39fe9e23d724de8516d/image","id":"511ac39fe9e23d724de8516d","name":"Tanlines"},"external_media":{"youtube":{"id":"kKJ3z9Pa7AU"}},"title":"All Of Me","cover_url":"http://images.mndigital.com/albums/064/954/295/g.jpeg","genre":"Alternative/Indie","pa":false,"quality_issues":[],"formats":[{"available":true,"format":"aac"},{"available":true,"format":"mp3"}],"duration":230,"new":false,"id":18827827,"added_by":null},{"album":"Business Casual","status":"ADD","artist":{"image_url":"http://songza.com/api/1/artist/511acd26e9e23d724dee5558/image","id":"511acd26e9e23d724dee5558","name":"Chromeo"},"external_media":{"youtube":{"id":"6XCcWlgVqHA"}},"title":"Night By Night","cover_url":"http://images.mndigital.com/albums/044/781/173/g.jpeg","genre":"Electronica/Dance","pa":false,"quality_issues":[],"formats":[{"available":true,"format":"aac"},{"available":true,"format":"mp3"}],"duration":227,"new":false,"id":16777531,"added_by":null},{"album":"A Joyful Noise","status":"ADD","artist":{"image_url":"http://songza.com/api/1/artist/511ace03e9e23d724deee01f/image","id":"511ace03e9e23d724deee01f","name":"Gossip"},"title":"Get A Job","cover_url":"http://images.mndigital.com/albums/068/262/029/g.jpeg","genre":"Alternative/Indie","pa":false,"quality_issues":[],"formats":[{"available":true,"format":"aac"},{"available":true,"format":"mp3"}],"duration":299,"new":false,"id":19766944,"added_by":null},{"album":"Music For Men","status":"ADD","artist":{"image_url":"http://songza.com/api/1/artist/511ace03e9e23d724deee01f/image","id":"511ace03e9e23d724deee01f","name":"Gossip"},"external_media":{"youtube":{"id":"IFLWfj_r7kY"}},"title":"Pop Goes The World","cover_url":"http://images.mndigital.com/albums/030/666/581/g.jpeg","genre":"Alternative/Indie","pa":false,"quality_issues":[],"formats":[{"available":true,"format":"aac"},{"available":true,"format":"mp3"}],"duration":203,"new":false,"id":5224688,"added_by":null},{"album":"Mixed Emotions","status":"ADD","artist":{"image_url":"http://songza.com/api/1/artist/511ac39fe9e23d724de8516d/image","id":"511ac39fe9e23d724de8516d","name":"Tanlines"},"title":"Lost Somewhere","cover_url":"http://images.mndigital.com/albums/064/954/295/g.jpeg","genre":"Alternative/Indie","pa":false,"quality_issues":[],"formats":[{"available":true,"format":"aac"},{"available":true,"format":"mp3"}],"duration":207,"new":false,"id":18822323,"added_by":null},{"album":"Manners","status":"ADD","artist":{"image_url":"http://songza.com/api/1/artist/511acd2de9e23d724dee59ba/image","id":"511acd2de9e23d724dee59ba","name":"Passion Pit"},"external_media":{"youtube":{"id":"ScC_pi3PJ9k"}},"title":"Little Secrets","cover_url":"http://images.mndigital.com/albums/069/488/105/g.jpeg","genre":"Alternative/Indie","pa":false,"quality_issues":[],"formats":[{"available":true,"format":"aac"},{"available":true,"format":"mp3"}],"duration":239,"new":false,"id":20326193,"added_by":null},{"album":"Cross","status":"ADD","artist":{"image_url":"http://songza.com/api/1/artist/511acbf4e9e23d724ded9054/image","id":"511acbf4e9e23d724ded9054","name":"Justice"},"external_media":{"youtube":{"id":"sy1dYFGkPUE"}},"title":"D.A.N.C.E.","cover_url":"http://images.mndigital.com/albums/011/106/333/g.jpeg","genre":"Electronica/Dance","pa":false,"quality_issues":[],"formats":[{"available":true,"format":"aac"},{"available":true,"format":"mp3"}],"duration":242,"new":false,"id":2217801,"added_by":null},{"album":"Flame","status":"ADD","artist":{"image_url":"http://songza.com/api/1/artist/511ac7b0e9e23d724deae787/image","id":"511ac7b0e9e23d724deae787","name":"Bell X1"},"external_media":{"youtube":{"id":"tCgKC_qSfY4"}},"title":"Flame (Chicken Lips Mix)","cover_url":"http://images.mndigital.com/albums/006/803/447/g.jpeg","genre":"Rock","pa":false,"quality_issues":[],"formats":[{"available":true,"format":"aac"},{"available":true,"format":"mp3"}],"duration":370,"new":false,"id":15116397,"added_by":null},{"album":"Hands (Us)","status":"ADD","artist":{"image_url":"http://songza.com/api/1/artist/511acbdee9e23d724ded82b0/image","id":"511acbdee9e23d724ded82b0","name":"Little Boots"},"title":"Remedy","cover_url":"http://images.mndigital.com/albums/037/640/413/g.jpeg","genre":"Pop","pa":false,"quality_issues":[],"formats":[{"available":true,"format":"aac"},{"available":true,"format":"mp3"}],"duration":200,"new":false,"id":7346757,"added_by":null},{"album":"The Bravery","status":"ADD","artist":{"image_url":"http://songza.com/api/1/artist/511acd40e9e23d724dee6689/image","id":"511acd40e9e23d724dee6689","name":"The Bravery"},"external_media":{"youtube":{"id":"O8vzbezVru4"}},"title":"An Honest Mistake","cover_url":"http://images.mndigital.com/albums/003/652/365/g.jpeg","genre":"Rock","pa":false,"quality_issues":[],"formats":[{"available":true,"format":"aac"},{"available":true,"format":"mp3"}],"duration":219,"new":false,"id":692055,"added_by":null},{"album":"Ladyhawke","status":"ADD","artist":{"image_url":"http://songza.com/api/1/artist/511acbcde9e23d724ded78fd/image","id":"511acbcde9e23d724ded78fd","name":"Ladyhawke"},"external_media":{"youtube":{"id":"3ccbj0A6NJI"}},"title":"Magic","cover_url":"http://images.mndigital.com/albums/019/834/899/g.jpeg","genre":"Pop","pa":false,"quality_issues":[],"formats":[{"available":true,"format":"aac"},{"available":true,"format":"mp3"}],"duration":209,"new":false,"id":3649635,"added_by":null},{"album":"Feel It Break","status":"ADD","artist":{"image_url":"http://songza.com/api/1/artist/511ac997e9e23d724dec1c98/image","id":"511ac997e9e23d724dec1c98","name":"Austra"},"title":"Lose It","cover_url":"http://images.mndigital.com/albums/102/046/953/g.jpeg","genre":"Alternative/Indie","pa":false,"quality_issues":[],"formats":[{"available":true,"format":"aac"},{"available":true,"format":"mp3"}],"duration":269,"new":false,"id":31152128,"added_by":null}]
