[{"album":"Any Way, Shape Or Form","status":"ADD","artist":{"image_url":"http://songza.com/api/1/artist/53d5cbc50ab19647724597e2/image","id":"53d5cbc50ab19647724597e2","name":"Ben Miller Band"},"title":"The Outsider","cover_url":"http://images.mndigital.com/albums/108/379/989/g.jpeg","genre":"Alternative/Indie","pa":false,"quality_issues":[],"formats":[{"available":true,"format":"aac"},{"available":true,"format":"mp3"}],"duration":187,"new":false,"id":32032917,"added_by":null},{"album":"One Lost Day","status":"ADD","artist":{"image_url":"http://songza.com/api/1/artist/511ace61e9e23d724def1632/image","id":"511ace61e9e23d724def1632","name":"Indigo Girls"},"title":"Elizabeth","cover_url":"http://images.mndigital.com/albums/170/585/303/g.jpeg","genre":"Alternative/Indie","pa":false,"quality_issues":[],"formats":[{"available":true,"format":"aac"},{"available":true,"format":"mp3"}],"duration":217,"new":false,"id":35850108,"added_by":null},{"album":"Not Here","status":"ADD","artist":{"image_url":"http://songza.com/api/1/artist/511ac1a6e9e23d724de7248b/image","id":"511ac1a6e9e23d724de7248b","name":"The Pollies"},"title":"Jackson","cover_url":"http://images.mndigital.com/albums/361/060/405/g.jpeg","genre":"Rock","pa":false,"quality_issues":[],"formats":[{"available":true,"format":"aac"},{"available":true,"format":"mp3"}],"duration":277,"new":false,"id":37600828,"added_by":null},{"album":"Bright As You Can","status":"ADD","artist":{"image_url":"http://songza.com/api/1/artist/5248f7f40ab19601d5b60ab6/image","id":"5248f7f40ab19601d5b60ab6","name":"The Mike"},"title":"Bright As You Can","cover_url":"http://images.mndigital.com/albums/130/556/281/g.jpeg","genre":"Folk","pa":false,"quality_issues":[],"formats":[{"available":true,"format":"aac"},{"available":true,"format":"mp3"}],"duration":182,"new":false,"id":35781270,"added_by":null},{"album":"Hwy 62","status":"ADD","artist":{"image_url":"http://songza.com/api/1/artist/511ac3b2e9e23d724de85dd5/image","id":"511ac3b2e9e23d724de85dd5","name":"Peter Case"},"title":"Pelican Bay","cover_url":"http://images.mndigital.com/albums/380/253/085/g.jpeg","genre":"Alternative/Indie","pa":false,"quality_issues":[],"formats":[{"available":true,"format":"aac"},{"available":true,"format":"mp3"}],"duration":237,"new":false,"id":39402907,"added_by":null},{"album":"Tomorrow Is My Turn","status":"ADD","artist":{"image_url":"http://songza.com/api/1/artist/528ed6490ab1967745756f3d/image","id":"528ed6490ab1967745756f3d","name":"Rhiannon Giddens"},"title":"Last Kind Words","cover_url":"http://images.mndigital.com/albums/124/505/981/g.jpeg","genre":"Folk","pa":false,"quality_issues":[],"formats":[{"available":true,"format":"aac"},{"available":true,"format":"mp3"}],"duration":254,"new":false,"id":34203910,"added_by":null},{"album":"Angeleno","status":"ADD","artist":{"image_url":"http://songza.com/api/1/artist/524e3b240ab196101b3a548c/image","id":"524e3b240ab196101b3a548c","name":"Sam Outlaw"},"title":"Angeleno","cover_url":"http://images.mndigital.com/albums/146/102/489/g.jpeg","genre":"Country","pa":false,"quality_issues":[],"formats":[{"available":true,"format":"aac"},{"available":true,"format":"mp3"}],"duration":240,"new":false,"id":36028488,"added_by":null},{"album":"Folk Singer Vol. 1","status":"ADD","artist":{"image_url":"http://songza.com/api/1/artist/53476c330ab19637972c58b7/image","id":"53476c330ab19637972c58b7","name":"Willie Watson"},"title":"Midnight Special","cover_url":"http://images.mndigital.com/albums/102/238/293/g.jpeg","genre":"Folk","pa":false,"quality_issues":[],"formats":[{"available":true,"format":"aac"},{"available":true,"format":"mp3"}],"duration":278,"new":false,"id":30589197,"added_by":null},{"album":"Glory Bound","status":"ADD","artist":{"image_url":"http://songza.com/api/1/artist/522169dfe9e23d469616b704/image","id":"522169dfe9e23d469616b704","name":"The Grahams"},"title":"Glory Bound","cover_url":"http://images.mndigital.com/albums/130/474/373/g.jpeg","genre":"Folk","pa":false,"quality_issues":[],"formats":[{"available":true,"format":"aac"},{"available":true,"format":"mp3"}],"duration":244,"new":false,"id":35518555,"added_by":null},{"album":"The Weather Below","status":"ADD","artist":{"image_url":"http://songza.com/api/1/artist/5239fcb40ab19672a83553b3/image","id":"5239fcb40ab19672a83553b3","name":"Sister Sparrow"},"title":"Mama Knows","cover_url":"http://images.mndigital.com/albums/130/224/903/g.jpeg","genre":"Rock","pa":false,"quality_issues":[],"formats":[{"available":true,"format":"aac"},{"available":true,"format":"mp3"}],"duration":212,"new":false,"id":35685176,"added_by":null},{"album":"Big Man","status":"ADD","artist":{"image_url":"http://songza.com/api/1/artist/511ac3d6e9e23d724de874ed/image","id":"511ac3d6e9e23d724de874ed","name":"Honeyhoney"},"title":"Big Man","cover_url":"http://images.mndigital.com/albums/153/954/547/g.jpeg","genre":"Alternative/Indie","pa":false,"quality_issues":[],"formats":[{"available":true,"format":"aac"},{"available":true,"format":"mp3"}],"duration":203,"new":false,"id":35619201,"added_by":null},{"album":"Gone Like The Cotton","status":"ADD","artist":{"image_url":"http://songza.com/api/1/artist/511ac9fce9e23d724dec5cd9/image","id":"511ac9fce9e23d724dec5cd9","name":"The Cox Family"},"title":"Gone Like The Cotton","cover_url":"http://images.mndigital.com/albums/379/987/543/g.jpeg","genre":"Folk","pa":false,"quality_issues":[],"formats":[{"available":true,"format":"aac"},{"available":true,"format":"mp3"}],"duration":243,"new":false,"id":39059606,"added_by":null},{"album":"Things That Can't Be Undone","status":"ADD","artist":{"image_url":"http://songza.com/api/1/artist/519cc78be9e23d5b23a87fa5/image","id":"519cc78be9e23d5b23a87fa5","name":"Corb Lund"},"title":"Washed-Up Rock Star Factory Blues","cover_url":"http://images.mndigital.com/albums/379/005/921/g.jpeg","genre":"Country","pa":false,"quality_issues":[],"formats":[{"available":true,"format":"aac"},{"available":true,"format":"mp3"}],"duration":253,"new":false,"id":38760745,"added_by":null},{"album":"Loved Wild Lost","status":"ADD","artist":{"image_url":"http://songza.com/api/1/artist/511aca0ee9e23d724dec68b2/image","id":"511aca0ee9e23d724dec68b2","name":"Nicki Bluhm"},"title":"Only Always","cover_url":"http://images.mndigital.com/albums/127/355/751/g.jpeg","genre":"Pop","pa":false,"quality_issues":[],"formats":[{"available":true,"format":"aac"},{"available":true,"format":"mp3"}],"duration":199,"new":false,"id":34715623,"added_by":null},{"album":"Something In The Water","status":"ADD","artist":{"image_url":"http://songza.com/api/1/artist/511acca4e9e23d724dee0218/image","id":"511acca4e9e23d724dee0218","name":"Pokey LaFarge"},"title":"Something In The Water","cover_url":"http://images.mndigital.com/albums/125/871/961/g.jpeg","genre":"Country","pa":false,"quality_issues":[],"formats":[{"available":true,"format":"aac"},{"available":true,"format":"mp3"}],"duration":202,"new":false,"id":34384925,"added_by":null},{"album":"Bittersweet","status":"ADD","artist":{"image_url":"http://songza.com/api/1/artist/511acce4e9e23d724dee2b8a/image","id":"511acce4e9e23d724dee2b8a","name":"Kasey Chambers"},"title":"Oh Grace","cover_url":"http://images.mndigital.com/albums/306/032/201/g.jpeg","genre":"Country","pa":false,"quality_issues":[],"formats":[{"available":true,"format":"aac"},{"available":true,"format":"mp3"}],"duration":262,"new":false,"id":37170353,"added_by":null},{"album":"Sound & Color","status":"ADD","artist":{"image_url":"http://songza.com/api/1/artist/511acc5ce9e23d724dedd2e4/image","id":"511acc5ce9e23d724dedd2e4","name":"Alabama Shakes"},"title":"This Feeling","cover_url":"http://images.mndigital.com/albums/130/047/491/g.jpeg","genre":"Alternative/Indie","pa":false,"quality_issues":[],"formats":[{"available":true,"format":"aac"},{"available":true,"format":"mp3"}],"duration":269,"new":false,"id":35253462,"added_by":null},{"album":"High On Tulsa Heat","status":"ADD","artist":{"image_url":"http://songza.com/api/1/artist/511ac69de9e23d724dea3c4b/image","id":"511ac69de9e23d724dea3c4b","name":"John Moreland"},"title":"High On Tulsa Heat","cover_url":"http://images.mndigital.com/albums/126/806/341/g.jpeg","genre":"Folk","pa":false,"quality_issues":[],"formats":[{"available":true,"format":"aac"},{"available":true,"format":"mp3"}],"duration":221,"new":false,"id":35140227,"added_by":null},{"album":"All Your Favorite Bands","status":"ADD","artist":{"image_url":"http://songza.com/api/1/artist/511acddde9e23d724deec7a9/image","id":"511acddde9e23d724deec7a9","name":"Dawes"},"title":"Things Happen","cover_url":"http://images.mndigital.com/albums/169/649/127/g.jpeg","genre":"Alternative/Indie","pa":false,"quality_issues":[],"formats":[{"available":true,"format":"aac"},{"available":true,"format":"mp3"}],"duration":244,"new":false,"id":35816238,"added_by":null},{"album":"In The Blazes","status":"ADD","artist":{"image_url":"http://songza.com/api/1/artist/511ac62fe9e23d724de9f5a3/image","id":"511ac62fe9e23d724de9f5a3","name":"Aaron Lee Tasjan"},"title":"The Trouble With Drinkin'","cover_url":"http://images.mndigital.com/albums/360/878/201/g.jpeg","genre":"Folk","pa":true,"quality_issues":[],"formats":[{"available":true,"format":"aac"},{"available":true,"format":"mp3"}],"duration":239,"new":false,"id":37599128,"added_by":null},{"album":"Gates Of Gold","status":"ADD","artist":{"image_url":"http://songza.com/api/1/artist/511acc9be9e23d724dedfc61/image","id":"511acc9be9e23d724dedfc61","name":"Los Lobos"},"title":"Gates Of Gold","cover_url":"http://images.mndigital.com/albums/378/354/189/g.jpeg","genre":"Alternative/Indie","pa":false,"quality_issues":[],"formats":[{"available":true,"format":"aac"},{"available":true,"format":"mp3"}],"duration":231,"new":false,"id":38553448,"added_by":null},{"album":"Remembering Mountains : Unheard Songs By Karen Dalton","status":"ADD","artist":{"image_url":"http://songza.com/api/1/artist/511acdcce9e23d724deebd7a/image","id":"511acdcce9e23d724deebd7a","name":"Patty Griffin"},"title":"All That Shines Is Not Truth","cover_url":"http://images.mndigital.com/albums/130/115/671/g.jpeg","genre":"Folk","pa":false,"quality_issues":[],"formats":[{"available":true,"format":"aac"},{"available":true,"format":"mp3"}],"duration":206,"new":false,"id":35376028,"added_by":null},{"album":"Soul Searching","status":"ADD","artist":{"image_url":"http://songza.com/api/1/artist/511ac7dde9e23d724deb04f4/image","id":"511ac7dde9e23d724deb04f4","name":"Jim Lauderdale"},"title":"Super Power","cover_url":"http://images.mndigital.com/albums/378/669/371/g.jpeg","genre":"Country","pa":false,"quality_issues":[],"formats":[{"available":true,"format":"aac"},{"available":true,"format":"mp3"}],"duration":131,"new":false,"id":38656182,"added_by":null},{"album":"Sermon On The Rocks","status":"ADD","artist":{"image_url":"http://songza.com/api/1/artist/511ace48e9e23d724def066a/image","id":"511ace48e9e23d724def066a","name":"Josh Ritter"},"title":"Getting Ready To Get Down","cover_url":"http://images.mndigital.com/albums/361/694/603/g.jpeg","genre":"Folk","pa":false,"quality_issues":[],"formats":[{"available":true,"format":"aac"},{"available":true,"format":"mp3"}],"duration":196,"new":false,"id":37606397,"added_by":null},{"album":"The Bell","status":"ADD","artist":{"image_url":"http://songza.com/api/1/artist/511ac518e9e23d724de94557/image","id":"511ac518e9e23d724de94557","name":"Tony Furtado"},"title":"Broken Bell","cover_url":"http://images.mndigital.com/albums/183/624/301/g.jpeg","genre":"Folk","pa":false,"quality_issues":[],"formats":[{"available":true,"format":"aac"},{"available":true,"format":"mp3"}],"duration":250,"new":false,"id":36236762,"added_by":null},{"album":"Meet Me In Bluesland","status":"ADD","artist":{"image_url":"http://songza.com/api/1/artist/519cca81e9e23d5b23a9a181/image","id":"519cca81e9e23d5b23a9a181","name":"The Kentucky Headhunters"},"title":"Stumblin'","cover_url":"http://images.mndigital.com/albums/147/683/301/g.jpeg","genre":"Blues","pa":false,"quality_issues":[],"formats":[{"available":true,"format":"aac"},{"available":true,"format":"mp3"}],"duration":188,"new":false,"id":35551768,"added_by":null},{"album":"Dirt Road's End","status":"ADD","artist":{"image_url":"http://songza.com/api/1/artist/511abb82e9e23d724de365f1/image","id":"511abb82e9e23d724de365f1","name":"Sugarcane Jane"},"title":"Ballad Of Sugarcane Jane","cover_url":"http://images.mndigital.com/albums/130/218/043/g.jpeg","genre":"Country","pa":false,"quality_issues":[],"formats":[{"available":true,"format":"aac"},{"available":true,"format":"mp3"}],"duration":309,"new":false,"id":35333234,"added_by":null},{"album":"From The Wreckage","status":"ADD","artist":{"image_url":"http://songza.com/api/1/artist/5340d9270ab1964ff238a944/image","id":"5340d9270ab1964ff238a944","name":"The Wind and The Wave"},"title":"Raising Hands Raising Hell Raise 'em High","cover_url":"http://images.mndigital.com/albums/107/972/675/g.jpeg","genre":"Alternative/Indie","pa":true,"quality_issues":[],"formats":[{"available":true,"format":"aac"},{"available":true,"format":"mp3"}],"duration":204,"new":false,"id":31997373,"added_by":null},{"album":"Slow Talker","status":"ADD","artist":{"image_url":"http://songza.com/api/1/artist/511acc7ae9e23d724dede6e0/image","id":"511acc7ae9e23d724dede6e0","name":"Jeffrey Foucault"},"title":"Slow Talker","cover_url":"http://images.mndigital.com/albums/378/285/715/g.jpeg","genre":"Blues","pa":false,"quality_issues":[],"formats":[{"available":true,"format":"aac"},{"available":true,"format":"mp3"}],"duration":237,"new":false,"id":38528209,"added_by":null},{"album":"Didn't It Rain","status":"ADD","artist":{"image_url":"http://songza.com/api/1/artist/511ac9bee9e23d724dec34aa/image","id":"511ac9bee9e23d724dec34aa","name":"Amy Helm"},"title":"Didn't It Rain","cover_url":"http://images.mndigital.com/albums/298/774/201/g.jpeg","genre":"Rock","pa":false,"quality_issues":[],"formats":[{"available":true,"format":"aac"},{"available":true,"format":"mp3"}],"duration":226,"new":false,"id":37152450,"added_by":null},{"album":"The Story Of Sonny Boy Slim","status":"ADD","artist":{"image_url":"http://songza.com/api/1/artist/511acb61e9e23d724ded323d/image","id":"511acb61e9e23d724ded323d","name":"Gary Clark Jr."},"title":"Shake","cover_url":"http://images.mndigital.com/albums/377/503/455/g.jpeg","genre":"Rock","pa":false,"quality_issues":[],"formats":[{"available":true,"format":"aac"},{"available":true,"format":"mp3"}],"duration":197,"new":false,"id":38047824,"added_by":null},{"album":"Can't Forget: A Souvenir Of The Grand Tour","status":"ADD","artist":{"image_url":"http://songza.com/api/1/artist/511ace4ae9e23d724def07ac/image","id":"511ace4ae9e23d724def07ac","name":"Leonard Cohen"},"title":"Choices (Live At Christchurch Soundcheck, 2013)","cover_url":"http://images.mndigital.com/albums/127/923/987/g.jpeg","genre":"Rock","pa":false,"quality_issues":[],"formats":[{"available":true,"format":"aac"},{"available":true,"format":"mp3"}],"duration":211,"new":false,"id":34632670,"added_by":null},{"album":"To Love Somebody","status":"ADD","artist":{"image_url":"http://songza.com/api/1/artist/511acd4de9e23d724dee6eaa/image","id":"511acd4de9e23d724dee6eaa","name":"Lindi Ortega"},"title":"To Love Somebody","cover_url":"http://images.mndigital.com/albums/166/548/207/g.jpeg","genre":"Country","pa":false,"quality_issues":[],"formats":[{"available":true,"format":"aac"},{"available":true,"format":"mp3"}],"duration":206,"new":false,"id":35759980,"added_by":null},{"album":"Link Of Chain - A Songwriters Tribute To Chris Smither","status":"ADD","artist":{"image_url":"http://songza.com/api/1/artist/511ace48e9e23d724def066a/image","id":"511ace48e9e23d724def066a","name":"Josh Ritter"},"title":"Rosalie","cover_url":"http://images.mndigital.com/albums/111/555/443/g.jpeg","genre":"Blues","pa":false,"quality_issues":[],"formats":[{"available":true,"format":"aac"},{"available":true,"format":"mp3"}],"duration":250,"new":false,"id":32411469,"added_by":null},{"album":"Gill Landry","status":"ADD","artist":{"image_url":"http://songza.com/api/1/artist/511ac74ae9e23d724deaa781/image","id":"511ac74ae9e23d724deaa781","name":"Gill Landry"},"title":"Funeral In My Heart","cover_url":"http://images.mndigital.com/albums/126/660/771/g.jpeg","genre":"Alternative/Indie","pa":false,"quality_issues":[],"formats":[{"available":true,"format":"aac"},{"available":true,"format":"mp3"}],"duration":111,"new":false,"id":34561536,"added_by":null},{"album":"Outskirts Of Love","status":"ADD","artist":{"image_url":"http://songza.com/api/1/artist/511ac115e9e23d724de6cf5b/image","id":"511ac115e9e23d724de6cf5b","name":"Shemekia Copeland"},"title":"Isn't That So","cover_url":"http://images.mndigital.com/albums/312/870/203/g.jpeg","genre":"Blues","pa":false,"quality_issues":[],"formats":[{"available":true,"format":"aac"},{"available":true,"format":"mp3"}],"duration":197,"new":false,"id":37173737,"added_by":null},{"album":"South Broadway Athletic Club","status":"ADD","artist":{"image_url":"http://songza.com/api/1/artist/511ac206e9e23d724de75b97/image","id":"511ac206e9e23d724de75b97","name":"The Bottle Rockets"},"title":"Monday (Everytime I Turn Around)","cover_url":"http://images.mndigital.com/albums/377/730/091/g.jpeg","genre":"Pop","pa":false,"quality_issues":[],"formats":[{"available":true,"format":"aac"},{"available":true,"format":"mp3"}],"duration":226,"new":false,"id":38170716,"added_by":null},{"album":"The Blade","status":"ADD","artist":{"image_url":"http://songza.com/api/1/artist/511ace75e9e23d724def2383/image","id":"511ace75e9e23d724def2383","name":"Ashley Monroe"},"title":"The Blade","cover_url":"http://images.mndigital.com/albums/280/110/201/g.jpeg","genre":"Country","pa":false,"quality_issues":[],"formats":[{"available":true,"format":"aac"},{"available":true,"format":"mp3"}],"duration":208,"new":false,"id":37116731,"added_by":null},{"album":"Turnpike Troubadours","status":"ADD","artist":{"image_url":"http://songza.com/api/1/artist/511acbe2e9e23d724ded84b8/image","id":"511acbe2e9e23d724ded84b8","name":"Turnpike Troubadours"},"title":"The Mercury","cover_url":"http://images.mndigital.com/albums/226/098/201/g.jpeg","genre":"Country","pa":false,"quality_issues":[],"formats":[{"available":true,"format":"aac"},{"available":true,"format":"mp3"}],"duration":223,"new":false,"id":37092510,"added_by":null},{"album":"Holdin' The Bag","status":"ADD","artist":{"image_url":"http://songza.com/api/1/artist/511ace1ee9e23d724deef058/image","id":"511ace1ee9e23d724deef058","name":"The Supersuckers"},"title":"Shimmy & Shake","cover_url":"http://images.mndigital.com/albums/377/428/705/g.jpeg","genre":"Country","pa":false,"quality_issues":[],"formats":[{"available":true,"format":"aac"},{"available":true,"format":"mp3"}],"duration":129,"new":false,"id":37984239,"added_by":null},{"album":"Imaginary Man","status":"ADD","artist":{"image_url":"http://songza.com/api/1/artist/511ac6dde9e23d724dea62a6/image","id":"511ac6dde9e23d724dea62a6","name":"Rayland Baxter"},"title":"Yellow Eyes","cover_url":"http://images.mndigital.com/albums/357/183/605/g.jpeg","genre":"Alternative/Indie","pa":false,"quality_issues":[],"formats":[{"available":true,"format":"aac"},{"available":true,"format":"mp3"}],"duration":231,"new":false,"id":37566396,"added_by":null},{"album":"Bright Shadow","status":"ADD","artist":{"image_url":"http://songza.com/api/1/artist/511ac9dbe9e23d724dec48c8/image","id":"511ac9dbe9e23d724dec48c8","name":"Ana Egge"},"title":"Bright Shadow","cover_url":"http://images.mndigital.com/albums/352/310/425/g.jpeg","genre":"Folk","pa":false,"quality_issues":[],"formats":[{"available":true,"format":"aac"},{"available":true,"format":"mp3"}],"duration":174,"new":false,"id":37495491,"added_by":null},{"album":"The Ruffian's Misfortune","status":"ADD","artist":{"image_url":"http://songza.com/api/1/artist/511ace4ee9e23d724def0a6c/image","id":"511ace4ee9e23d724def0a6c","name":"Ray Wylie Hubbard"},"title":"All Loose Things","cover_url":"http://images.mndigital.com/albums/127/251/095/g.jpeg","genre":"Folk","pa":false,"quality_issues":[],"formats":[{"available":true,"format":"aac"},{"available":true,"format":"mp3"}],"duration":215,"new":false,"id":35210889,"added_by":null},{"album":"The Loneliest Man I Ever Met","status":"ADD","artist":{"image_url":"http://songza.com/api/1/artist/511acc78e9e23d724dede533/image","id":"511acc78e9e23d724dede533","name":"Kinky Friedman"},"title":"Bloody Mary Morning","cover_url":"http://images.mndigital.com/albums/377/076/921/g.jpeg","genre":"Country","pa":false,"quality_issues":[],"formats":[{"available":true,"format":"aac"},{"available":true,"format":"mp3"}],"duration":188,"new":false,"id":37849764,"added_by":null},{"album":"Chapter Two","status":"ADD","artist":{"image_url":"http://songza.com/api/1/artist/511ab1fee9e23d724dddd9b9/image","id":"511ab1fee9e23d724dddd9b9","name":"Carolina Story"},"title":"Almost Over Now","cover_url":"http://images.mndigital.com/albums/105/916/831/g.jpeg","genre":"Folk","pa":false,"quality_issues":[],"formats":[{"available":true,"format":"aac"},{"available":true,"format":"mp3"}],"duration":181,"new":false,"id":31452648,"added_by":null},{"album":"Lost Time","status":"ADD","artist":{"image_url":"http://songza.com/api/1/artist/511acc4fe9e23d724dedca89/image","id":"511acc4fe9e23d724dedca89","name":"Dave Alvin"},"title":"Mister Kicks","cover_url":"http://images.mndigital.com/albums/200/379/323/g.jpeg","genre":"Blues","pa":false,"quality_issues":[],"formats":[{"available":true,"format":"aac"},{"available":true,"format":"mp3"}],"duration":221,"new":false,"id":36868364,"added_by":null},{"album":"Under Branch & Thorn & Tree","status":"ADD","artist":{"image_url":"http://songza.com/api/1/artist/511acc56e9e23d724dedceec/image","id":"511acc56e9e23d724dedceec","name":"Samantha Crain"},"title":"Kathleen","cover_url":"http://images.mndigital.com/albums/184/416/201/g.jpeg","genre":"Rock","pa":false,"quality_issues":[],"formats":[{"available":true,"format":"aac"},{"available":true,"format":"mp3"}],"duration":202,"new":false,"id":36329550,"added_by":null},{"album":"Me Oh My","status":"ADD","artist":{"image_url":"http://songza.com/api/1/artist/511ab43ce9e23d724ddf23c1/image","id":"511ab43ce9e23d724ddf23c1","name":"The Honeycutters"},"title":"Jukebox","cover_url":"http://images.mndigital.com/albums/127/154/119/g.jpeg","genre":"Country","pa":false,"quality_issues":[],"formats":[{"available":true,"format":"aac"},{"available":true,"format":"mp3"}],"duration":276,"new":false,"id":34580526,"added_by":null},{"album":"Cass County (Deluxe)","status":"ADD","artist":{"image_url":"http://songza.com/api/1/artist/511ac92ee9e23d724debd8ec/image","id":"511ac92ee9e23d724debd8ec","name":"Don Henley"},"title":"She Sang Hymns Out Of Tune","cover_url":"http://images.mndigital.com/albums/378/368/931/g.jpeg","genre":"Country","pa":false,"quality_issues":[],"formats":[{"available":true,"format":"aac"},{"available":true,"format":"mp3"}],"duration":196,"new":false,"id":38598414,"added_by":null},{"album":"It's Great To Be Alive! (Deluxe)","status":"ADD","artist":{"image_url":"http://songza.com/api/1/artist/511acce9e9e23d724dee2ee1/image","id":"511acce9e9e23d724dee2ee1","name":"Drive-By Truckers"},"title":"Runaway Train","cover_url":"http://images.mndigital.com/albums/380/444/791/g.jpeg","genre":"Alternative/Indie","pa":false,"quality_issues":[],"formats":[{"available":true,"format":"aac"},{"available":true,"format":"mp3"}],"duration":335,"new":false,"id":39200890,"added_by":null},{"album":"Hard To Please","status":"ADD","artist":{"image_url":"http://songza.com/api/1/artist/511abc08e9e23d724de3bba0/image","id":"511abc08e9e23d724de3bba0","name":"The Black Lillies"},"title":"Hard To Please","cover_url":"http://images.mndigital.com/albums/371/447/287/g.jpeg","genre":"Rock","pa":false,"quality_issues":[],"formats":[{"available":true,"format":"aac"},{"available":true,"format":"mp3"}],"duration":251,"new":false,"id":37776505,"added_by":null},{"album":"Paradise","status":"ADD","artist":{"image_url":"http://songza.com/api/1/artist/511accfbe9e23d724dee39cd/image","id":"511accfbe9e23d724dee39cd","name":"The Wood Brothers"},"title":"Snake Eyes","cover_url":"http://images.mndigital.com/albums/367/238/201/g.jpeg","genre":"Country","pa":false,"quality_issues":[],"formats":[{"available":true,"format":"aac"},{"available":true,"format":"mp3"}],"duration":211,"new":false,"id":37720184,"added_by":null},{"album":"Medicine","status":"ADD","artist":{"image_url":"http://songza.com/api/1/artist/511abea5e9e23d724de5591e/image","id":"511abea5e9e23d724de5591e","name":"Drew Holcomb & The Neighbors"},"title":"American Beauty","cover_url":"http://images.mndigital.com/albums/114/639/133/g.jpeg","genre":"Folk","pa":false,"quality_issues":[],"formats":[{"available":true,"format":"aac"},{"available":true,"format":"mp3"}],"duration":158,"new":false,"id":32839222,"added_by":null},{"album":"Squelch","status":"ADD","artist":{"image_url":"http://songza.com/api/1/artist/511accb7e9e23d724dee0e3f/image","id":"511accb7e9e23d724dee0e3f","name":"Jason Boland & The Stragglers"},"title":"Lose Early","cover_url":"http://images.mndigital.com/albums/377/495/559/g.jpeg","genre":"Country","pa":false,"quality_issues":[],"formats":[{"available":true,"format":"aac"},{"available":true,"format":"mp3"}],"duration":272,"new":false,"id":38046015,"added_by":null},{"album":"Banditos","status":"ADD","artist":{"image_url":"http://songza.com/api/1/artist/511ac17fe9e23d724de70cab/image","id":"511ac17fe9e23d724de70cab","name":"Banditos"},"title":"The Breeze","cover_url":"http://images.mndigital.com/albums/142/642/201/g.jpeg","genre":"Pop","pa":false,"quality_issues":[],"formats":[{"available":true,"format":"aac"},{"available":true,"format":"mp3"}],"duration":233,"new":false,"id":35479379,"added_by":null},{"album":"Remembering Mountains : Unheard Songs By Karen Dalton","status":"ADD","artist":{"image_url":"http://songza.com/api/1/artist/511ace37e9e23d724def0057/image","id":"511ace37e9e23d724def0057","name":"Lucinda Williams"},"title":"Met An Old Friend","cover_url":"http://images.mndigital.com/albums/130/115/671/g.jpeg","genre":"Folk","pa":false,"quality_issues":[],"formats":[{"available":true,"format":"aac"},{"available":true,"format":"mp3"}],"duration":232,"new":false,"id":35376036,"added_by":null},{"album":"Before This World","status":"ADD","artist":{"image_url":"http://songza.com/api/1/artist/511acdf3e9e23d724deed624/image","id":"511acdf3e9e23d724deed624","name":"James Taylor"},"title":"Today Today Today","cover_url":"http://images.mndigital.com/albums/183/716/211/g.jpeg","genre":"Pop","pa":false,"quality_issues":[],"formats":[{"available":true,"format":"aac"},{"available":true,"format":"mp3"}],"duration":189,"new":false,"id":36238170,"added_by":null},{"album":"Wilder Mind","status":"ADD","artist":{"image_url":"http://songza.com/api/1/artist/511ace47e9e23d724def0627/image","id":"511ace47e9e23d724def0627","name":"Mumford & Sons"},"title":"Ditmas","cover_url":"http://images.mndigital.com/albums/143/110/301/g.jpeg","genre":"Alternative/Indie","pa":false,"quality_issues":[],"formats":[{"available":true,"format":"aac"},{"available":true,"format":"mp3"}],"duration":219,"new":false,"id":35482071,"added_by":null},{"album":"Too High","status":"ADD","artist":{"image_url":"http://songza.com/api/1/artist/511acc6de9e23d724deddddd/image","id":"511acc6de9e23d724deddddd","name":"Blackberry Smoke"},"title":"Too High","cover_url":"http://images.mndigital.com/albums/123/662/571/g.jpeg","genre":"Rock","pa":false,"quality_issues":[],"formats":[{"available":true,"format":"aac"},{"available":true,"format":"mp3"}],"duration":192,"new":false,"id":34030028,"added_by":null},{"album":"Push And Pull (All The Time)","status":"ADD","artist":{"image_url":"http://songza.com/api/1/artist/5218324ae9e23d0c7533aa55/image","id":"5218324ae9e23d0c7533aa55","name":"Promised Land Sound"},"title":"Push And Pull (All The Time)","cover_url":"http://images.mndigital.com/albums/378/963/227/g.jpeg","genre":"Alternative/Indie","pa":false,"quality_issues":[],"formats":[{"available":true,"format":"aac"},{"available":true,"format":"mp3"}],"duration":312,"new":false,"id":38747062,"added_by":null},{"album":"All Your Favorite Bands","status":"ADD","artist":{"image_url":"http://songza.com/api/1/artist/511acddde9e23d724deec7a9/image","id":"511acddde9e23d724deec7a9","name":"Dawes"},"title":"All Your Favorite Bands","cover_url":"http://images.mndigital.com/albums/169/649/127/g.jpeg","genre":"Alternative/Indie","pa":false,"quality_issues":[],"formats":[{"available":true,"format":"aac"},{"available":true,"format":"mp3"}],"duration":216,"new":false,"id":35816245,"added_by":null},{"album":"Still","status":"ADD","artist":{"image_url":"http://songza.com/api/1/artist/511acd4ce9e23d724dee6dc4/image","id":"511acd4ce9e23d724dee6dc4","name":"Richard Thompson"},"title":"Beatnik Walking","cover_url":"http://images.mndigital.com/albums/188/646/465/g.jpeg","genre":"Rock","pa":false,"quality_issues":[],"formats":[{"available":true,"format":"aac"},{"available":true,"format":"mp3"}],"duration":234,"new":false,"id":36546986,"added_by":null},{"album":"Uncovered","status":"ADD","artist":{"image_url":"http://songza.com/api/1/artist/511ace78e9e23d724def250e/image","id":"511ace78e9e23d724def250e","name":"Shawn Colvin"},"title":"Acadian Driftwood","cover_url":"http://images.mndigital.com/albums/378/397/973/g.jpeg","genre":"Alternative/Indie","pa":false,"quality_issues":[],"formats":[{"available":true,"format":"aac"},{"available":true,"format":"mp3"}],"duration":389,"new":false,"id":38573075,"added_by":null},{"album":"Going Down To The River","status":"ADD","artist":{"image_url":"http://songza.com/api/1/artist/53feae730ab196748bb41011/image","id":"53feae730ab196748bb41011","name":"Doug Seegers"},"title":"Going Down To The River","cover_url":"http://images.mndigital.com/albums/114/062/719/g.jpeg","genre":"Country","pa":false,"quality_issues":[],"formats":[{"available":true,"format":"aac"},{"available":true,"format":"mp3"}],"duration":254,"new":false,"id":32784455,"added_by":null},{"album":"Mystery Glue","status":"ADD","artist":{"image_url":"http://songza.com/api/1/artist/511acdcfe9e23d724deebf12/image","id":"511acdcfe9e23d724deebf12","name":"Graham Parker & The Rumour"},"title":"Transit Of Venus","cover_url":"http://images.mndigital.com/albums/153/975/323/g.jpeg","genre":"Rock","pa":false,"quality_issues":[],"formats":[{"available":true,"format":"aac"},{"available":true,"format":"mp3"}],"duration":222,"new":false,"id":35619528,"added_by":null},{"album":"The Traveling Kind","status":"ADD","artist":{"image_url":"http://songza.com/api/1/artist/511acd93e9e23d724dee99bb/image","id":"511acd93e9e23d724dee99bb","name":"Emmylou Harris"},"title":"The Traveling Kind","cover_url":"http://images.mndigital.com/albums/128/821/409/g.jpeg","genre":"Country","pa":false,"quality_issues":[],"formats":[{"available":true,"format":"aac"},{"available":true,"format":"mp3"}],"duration":221,"new":false,"id":34878294,"added_by":null},{"album":"Remedy","status":"ADD","artist":{"image_url":"http://songza.com/api/1/artist/511acb3de9e23d724ded1ac0/image","id":"511acb3de9e23d724ded1ac0","name":"Old Crow Medicine Show"},"title":"Sweet Amarillo","cover_url":"http://images.mndigital.com/albums/106/909/999/g.jpeg","genre":"Country","pa":false,"quality_issues":[],"formats":[{"available":true,"format":"aac"},{"available":true,"format":"mp3"}],"duration":203,"new":false,"id":31657443,"added_by":null},{"album":"My Stupid Heart","status":"ADD","artist":{"image_url":"http://songza.com/api/1/artist/511acdd5e9e23d724deec2a2/image","id":"511acdd5e9e23d724deec2a2","name":"Shawn Mullins"},"title":"My Stupid Heart","cover_url":"http://images.mndigital.com/albums/379/987/513/g.jpeg","genre":"Folk","pa":false,"quality_issues":[],"formats":[{"available":true,"format":"aac"},{"available":true,"format":"mp3"}],"duration":205,"new":false,"id":39059585,"added_by":null},{"album":"Wilder Mind","status":"ADD","artist":{"image_url":"http://songza.com/api/1/artist/511ace47e9e23d724def0627/image","id":"511ace47e9e23d724def0627","name":"Mumford & Sons"},"title":"Wilder Mind","cover_url":"http://images.mndigital.com/albums/143/110/301/g.jpeg","genre":"Alternative/Indie","pa":false,"quality_issues":[],"formats":[{"available":true,"format":"aac"},{"available":true,"format":"mp3"}],"duration":278,"new":false,"id":35482061,"added_by":null},{"album":"The Embers Of Time","status":"ADD","artist":{"image_url":"http://songza.com/api/1/artist/511ace19e9e23d724deeed54/image","id":"511ace19e9e23d724deeed54","name":"Josh Rouse"},"title":"Time","cover_url":"http://images.mndigital.com/albums/123/561/215/g.jpeg","genre":"Alternative/Indie","pa":false,"quality_issues":[],"formats":[{"available":true,"format":"aac"},{"available":true,"format":"mp3"}],"duration":193,"new":false,"id":34005022,"added_by":null},{"album":"Something More Than Free","status":"ADD","artist":{"image_url":"http://songza.com/api/1/artist/511acd42e9e23d724dee6852/image","id":"511acd42e9e23d724dee6852","name":"Jason Isbell"},"title":"If It Takes A Lifetime","cover_url":"http://images.mndigital.com/albums/134/942/261/g.jpeg","genre":"Folk","pa":false,"quality_issues":[],"formats":[{"available":true,"format":"aac"},{"available":true,"format":"mp3"}],"duration":220,"new":false,"id":35520980,"added_by":null},{"album":"Lost On The River","status":"ADD","artist":{"image_url":"http://songza.com/api/1/artist/53eaeb1a0ab1967995be9119/image","id":"53eaeb1a0ab1967995be9119","name":"The New Basement Tapes"},"title":"Stranger","cover_url":"http://images.mndigital.com/albums/117/602/227/g.jpeg","genre":"Alternative/Indie","pa":false,"quality_issues":[],"formats":[{"available":true,"format":"aac"},{"available":true,"format":"mp3"}],"duration":262,"new":false,"id":33135304,"added_by":null},{"album":"Radio","status":"ADD","artist":{"image_url":"http://songza.com/api/1/artist/511abcb1e9e23d724de41d74/image","id":"511abcb1e9e23d724de41d74","name":"Steep Canyon Rangers"},"title":"Radio","cover_url":"http://images.mndigital.com/albums/373/256/887/g.jpeg","genre":"Folk","pa":false,"quality_issues":[],"formats":[{"available":true,"format":"aac"},{"available":true,"format":"mp3"}],"duration":205,"new":false,"id":37771039,"added_by":null},{"album":"Della Mae","status":"ADD","artist":{"image_url":"http://songza.com/api/1/artist/511ab84de9e23d724de186ee/image","id":"511ab84de9e23d724de186ee","name":"Della Mae"},"title":"Boston Town","cover_url":"http://images.mndigital.com/albums/148/627/767/g.jpeg","genre":"Folk","pa":false,"quality_issues":[],"formats":[{"available":true,"format":"aac"},{"available":true,"format":"mp3"}],"duration":204,"new":false,"id":35536148,"added_by":null},{"album":"Then Came The Morning","status":"ADD","artist":{"image_url":"http://songza.com/api/1/artist/511acde5e9e23d724deeccd4/image","id":"511acde5e9e23d724deeccd4","name":"The Lone Bellow"},"title":"Then Came The Morning","cover_url":"http://images.mndigital.com/albums/118/770/735/g.jpeg","genre":"Alternative/Indie","pa":false,"quality_issues":[],"formats":[{"available":true,"format":"aac"},{"available":true,"format":"mp3"}],"duration":251,"new":false,"id":33277929,"added_by":null},{"album":"Faded Gloryville","status":"ADD","artist":{"image_url":"http://songza.com/api/1/artist/511acd4de9e23d724dee6eaa/image","id":"511acd4de9e23d724dee6eaa","name":"Lindi Ortega"},"title":"Ashes","cover_url":"http://images.mndigital.com/albums/354/901/801/g.jpeg","genre":"Country","pa":false,"quality_issues":[],"formats":[{"available":true,"format":"aac"},{"available":true,"format":"mp3"}],"duration":272,"new":false,"id":37521964,"added_by":null},{"album":"Primrose Green","status":"ADD","artist":{"image_url":"http://songza.com/api/1/artist/523bc8bb0ab1962ffdc73ae1/image","id":"523bc8bb0ab1962ffdc73ae1","name":"Ryley Walker"},"title":"On The Banks Of The Old Kishwaukee","cover_url":"http://images.mndigital.com/albums/127/599/521/g.jpeg","genre":"Rock","pa":false,"quality_issues":[],"formats":[{"available":true,"format":"aac"},{"available":true,"format":"mp3"}],"duration":300,"new":false,"id":34604524,"added_by":null},{"album":"Water Walker","status":"ADD","artist":{"image_url":"http://songza.com/api/1/artist/511ab3c8e9e23d724ddedbdc/image","id":"511ab3c8e9e23d724ddedbdc","name":"Folk Family Revival"},"title":"Sunshine","cover_url":"http://images.mndigital.com/albums/129/072/271/g.jpeg","genre":"Folk","pa":false,"quality_issues":[],"formats":[{"available":true,"format":"aac"},{"available":true,"format":"mp3"}],"duration":181,"new":false,"id":34891048,"added_by":null},{"album":"The Firewatcher's Daughter","status":"ADD","artist":{"image_url":"http://songza.com/api/1/artist/511acd24e9e23d724dee5480/image","id":"511acd24e9e23d724dee5480","name":"Brandi Carlile"},"title":"The Things I Regret","cover_url":"http://images.mndigital.com/albums/126/834/219/g.jpeg","genre":"Alternative/Indie","pa":false,"quality_issues":[],"formats":[{"available":true,"format":"aac"},{"available":true,"format":"mp3"}],"duration":206,"new":false,"id":34546216,"added_by":null},{"album":"Something More Than Free","status":"ADD","artist":{"image_url":"http://songza.com/api/1/artist/511acd42e9e23d724dee6852/image","id":"511acd42e9e23d724dee6852","name":"Jason Isbell"},"title":"To A Band That I Loved","cover_url":"http://images.mndigital.com/albums/134/942/261/g.jpeg","genre":"Folk","pa":false,"quality_issues":[],"formats":[{"available":true,"format":"aac"},{"available":true,"format":"mp3"}],"duration":233,"new":false,"id":35520990,"added_by":null},{"album":"Still The King: Celebrating The Music Of Bob Wills And His Texas Playboys","status":"ADD","artist":{"image_url":"http://songza.com/api/1/artist/511ace49e9e23d724def0782/image","id":"511ace49e9e23d724def0782","name":"Asleep At The Wheel"},"title":"The Girl I Left Behind Me (Feat. The Avett Brothers)","cover_url":"http://images.mndigital.com/albums/125/587/583/g.jpeg","genre":"Country","pa":false,"quality_issues":[],"formats":[{"available":true,"format":"aac"},{"available":true,"format":"mp3"}],"duration":151,"new":false,"id":34361456,"added_by":null},{"album":"Reinventing Richard","status":"ADD","artist":{"image_url":"http://songza.com/api/1/artist/511acb3fe9e23d724ded1c47/image","id":"511acb3fe9e23d724ded1c47","name":"Plainsong"},"title":"Pack Up Your Sorrows","cover_url":"http://images.mndigital.com/albums/377/678/621/g.jpeg","genre":"Folk","pa":false,"quality_issues":[],"formats":[{"available":true,"format":"aac"},{"available":true,"format":"mp3"}],"duration":290,"new":false,"id":38152609,"added_by":null},{"album":"Tomorrow You're Going (Feat. Lucy Kaplansky & Richard Shindell)","status":"ADD","artist":{"image_url":"http://songza.com/api/1/artist/54c86b290ab1961c31e18528/image","id":"54c86b290ab1961c31e18528","name":"Pine Hill Project"},"title":"I Live On A Battlefield (Feat. Lucy Kaplansky & Richard Shindell)","cover_url":"http://images.mndigital.com/albums/124/525/477/g.jpeg","genre":"Folk","pa":false,"quality_issues":[],"formats":[{"available":true,"format":"aac"},{"available":true,"format":"mp3"}],"duration":215,"new":false,"id":34204961,"added_by":null},{"album":"Sonic Ranch","status":"ADD","artist":{"image_url":"http://songza.com/api/1/artist/511ac62ee9e23d724de9f49e/image","id":"511ac62ee9e23d724de9f49e","name":"Whitey Morgan & The 78's"},"title":"Goin' Down Rocking","cover_url":"http://images.mndigital.com/albums/130/153/275/g.jpeg","genre":"Country","pa":true,"quality_issues":[],"formats":[{"available":true,"format":"aac"},{"available":true,"format":"mp3"}],"duration":219,"new":false,"id":35260140,"added_by":null},{"album":"Béla Fleck & Abigail Washburn","status":"ADD","artist":{"image_url":"http://songza.com/api/1/artist/511acce2e9e23d724dee2a77/image","id":"511acce2e9e23d724dee2a77","name":"Béla Fleck"},"title":"Railroad","cover_url":"http://images.mndigital.com/albums/114/062/867/g.jpeg","genre":"Folk","pa":false,"quality_issues":[],"formats":[{"available":true,"format":"aac"},{"available":true,"format":"mp3"}],"duration":216,"new":false,"id":32783508,"added_by":null},{"album":"Jekyll + Hyde","status":"ADD","artist":{"image_url":"http://songza.com/api/1/artist/511acdd4e9e23d724deec1cd/image","id":"511acdd4e9e23d724deec1cd","name":"Zac Brown Band"},"title":"Castaway","cover_url":"http://images.mndigital.com/albums/133/628/211/g.jpeg","genre":"Country","pa":false,"quality_issues":[],"formats":[{"available":true,"format":"aac"},{"available":true,"format":"mp3"}],"duration":188,"new":false,"id":35364807,"added_by":null},{"album":"Coming Home","status":"ADD","artist":{"image_url":"http://songza.com/api/1/artist/54c86b290ab1961c31e187e1/image","id":"54c86b290ab1961c31e187e1","name":"Leon Bridges"},"title":"Better Man","cover_url":"http://images.mndigital.com/albums/189/759/321/g.jpeg","genre":"Soul/R&B","pa":false,"quality_issues":[],"formats":[{"available":true,"format":"aac"},{"available":true,"format":"mp3"}],"duration":141,"new":false,"id":36528662,"added_by":null},{"album":"Gary Clark Jr. Live","status":"ADD","artist":{"image_url":"http://songza.com/api/1/artist/511acb61e9e23d724ded323d/image","id":"511acb61e9e23d724ded323d","name":"Gary Clark Jr."},"title":"Catfish Blues (Live)","cover_url":"http://images.mndigital.com/albums/112/386/153/g.jpeg","genre":"Alternative/Indie","pa":false,"quality_issues":[],"formats":[{"available":true,"format":"aac"},{"available":true,"format":"mp3"}],"duration":481,"new":false,"id":32583165,"added_by":null},{"album":"Live At Red Rocks With The Colorado Symphony","status":"ADD","artist":{"image_url":"http://songza.com/api/1/artist/511ace50e9e23d724def0bef/image","id":"511ace50e9e23d724def0bef","name":"Amos Lee"},"title":"Colors (Live)","cover_url":"http://images.mndigital.com/albums/182/688/731/g.jpeg","genre":"Alternative/Indie","pa":false,"quality_issues":[],"formats":[{"available":true,"format":"aac"},{"available":true,"format":"mp3"}],"duration":181,"new":false,"id":36429615,"added_by":null},{"album":"Free","status":"ADD","artist":{"image_url":"http://songza.com/api/1/artist/511acce2e9e23d724dee29d9/image","id":"511acce2e9e23d724dee29d9","name":"Cody Simpson"},"title":"Driftwood","cover_url":"http://images.mndigital.com/albums/196/114/491/g.jpeg","genre":"Rock","pa":false,"quality_issues":[],"formats":[{"available":true,"format":"aac"},{"available":true,"format":"mp3"}],"duration":223,"new":false,"id":36713290,"added_by":null},{"album":"Sing Into My Mouth","status":"ADD","artist":{"image_url":"http://songza.com/api/1/artist/511acce5e9e23d724dee2c86/image","id":"511acce5e9e23d724dee2c86","name":"Iron & Wine"},"title":"Done This One Before","cover_url":"http://images.mndigital.com/albums/233/283/599/g.jpeg","genre":"Alternative/Indie","pa":false,"quality_issues":[],"formats":[{"available":true,"format":"aac"},{"available":true,"format":"mp3"}],"duration":179,"new":false,"id":37005290,"added_by":null}]
